mes_fichiers
