Metadata-Version: 1.1
Name: django-mes-fichiers
Version: 0.1.1
Summary: Manager for files and albums with tinymce integration
Home-page: https://github.com/pavelulyashev/django-mes-fichiers
Author: Pavel Ulyashev
Author-email: p.ulyashev@gmail.com
License: BSD
Platform: any
Classifier: Programming Language :: Python
Classifier: Framework :: Django
Classifier: Development Status :: 4 - Beta
Classifier: Environment :: Web Environment
Classifier: Intended Audience :: Developers
Classifier: License :: OSI Approved :: BSD License
Classifier: Operating System :: OS Independent
Classifier: Topic :: Software Development
